[
    {
        "owner_name": "Jeff S.",
        "business_name": "Jeff Settle Rental Friends Denver",
        "business_website": "rentalfriends.net",
        "yelp_website": "https://www.yelp.com/biz/jeff-settle-rental-friends-denver?osq=Real+estate",
        "phone_number": "(720) 918-2328",
        "review_rating": null,
        "number_of_reviews": 10,
        "business_categories": [],
        "reviews": [
            {
                "user_name": null,
                "user_location": null,
                "review_date": null,
                "rating": "5 star rating",
                "review_text": null
            },
            {
                "user_name": null,
                "user_location": null,
                "review_date": null,
                "rating": "5 star rating",
                "review_text": null
            },
            {
                "user_name": null,
                "user_location": null,
                "review_date": null,
                "rating": "5 star rating",
                "review_text": null
            },
            {
                "user_name": null,
                "user_location": null,
                "review_date": null,
                "rating": "5 star rating",
                "review_text": null
            },
            {
                "user_name": null,
                "user_location": null,
                "review_date": null,
                "rating": "5 star rating",
                "review_text": null
            },
            {
                "user_name": null,
                "user_location": null,
                "review_date": null,
                "rating": "5 star rating",
                "review_text": null
            },
            {
                "user_name": null,
                "user_location": null,
                "review_date": null,
                "rating": "5 star rating",
                "review_text": null
            },
            {
                "user_name": null,
                "user_location": null,
                "review_date": null,
                "rating": "5 star rating",
                "review_text": null
            },
            {
                "user_name": null,
                "user_location": null,
                "review_date": null,
                "rating": "5 star rating",
                "review_text": null
            },
            {
                "user_name": null,
                "user_location": null,
                "review_date": null,
                "rating": "5 star rating",
                "review_text": null
            }
        ],
        "address": "1547 Gaylord St Ste B1 & B2 Ste B1 & B2 Denver, CO 80206",
        "work_hours": []
    },
    {
        "owner_name": "Lydia L.",
        "business_name": "Lydia Lin One Realty Denver 2",
        "business_website": "onerealtydenver.com",
        "yelp_website": "https://www.yelp.com/biz/lydia-lin-one-realty-denver-2?osq=Real+estate",
        "phone_number": "(720) 940-9590",
        "review_rating": null,
        "number_of_reviews": 10,
        "business_categories": [],
        "reviews": [
            {
                "user_name": null,
                "user_location": null,
                "review_date": null,
                "rating": "5 star rating",
                "review_text": null
            },
            {
                "user_name": null,
                "user_location": null,
                "review_date": null,
                "rating": "5 star rating",
                "review_text": null
            },
            {
                "user_name": null,
                "user_location": null,
                "review_date": null,
                "rating": "5 star rating",
                "review_text": null
            },
            {
                "user_name": null,
                "user_location": null,
                "review_date": null,
                "rating": "5 star rating",
                "review_text": null
            },
            {
                "user_name": null,
                "user_location": null,
                "review_date": null,
                "rating": "5 star rating",
                "review_text": null
            },
            {
                "user_name": null,
                "user_location": null,
                "review_date": null,
                "rating": "5 star rating",
                "review_text": null
            },
            {
                "user_name": null,
                "user_location": null,
                "review_date": null,
                "rating": "5 star rating",
                "review_text": null
            },
            {
                "user_name": null,
                "user_location": null,
                "review_date": null,
                "rating": "5 star rating",
                "review_text": null
            },
            {
                "user_name": null,
                "user_location": null,
                "review_date": null,
                "rating": "5 star rating",
                "review_text": null
            },
            {
                "user_name": null,
                "user_location": null,
                "review_date": null,
                "rating": "5 star rating",
                "review_text": null
            }
        ],
        "address": "2546 15th St Ste 200 Denver, CO 80211",
        "work_hours": [
            "Mon: 8:00 AM - 9:00 PM",
            "Tue: 8:00 AM - 9:00 PM",
            "Wed: 8:00 AM - 9:00 PM",
            "Thu: 8:00 AM - 9:00 PM",
            "Fri: 8:00 AM - 9:00 PM",
            "Sat: 9:00 AM - 8:00 PM",
            "Sun: 9:00 AM - 8:00 PM"
        ]
    },
    {
        "owner_name": "Community Team",
        "business_name": "Creekside Denver 3",
        "business_website": "creeksideapartmenthomes.com",
        "yelp_website": "https://www.yelp.com/biz/creekside-denver-3?osq=Real+estate",
        "phone_number": "(720) 605-6743",
        "review_rating": null,
        "number_of_reviews": 12,
        "business_categories": [],
        "reviews": [
            {
                "user_name": null,
                "user_location": null,
                "review_date": null,
                "rating": null,
                "review_text": null
            },
            {
                "user_name": null,
                "user_location": null,
                "review_date": null,
                "rating": null,
                "review_text": null
            },
            {
                "user_name": null,
                "user_location": null,
                "review_date": null,
                "rating": "4 star rating",
                "review_text": null
            },
            {
                "user_name": null,
                "user_location": null,
                "review_date": null,
                "rating": "1 star rating",
                "review_text": null
            },
            {
                "user_name": null,
                "user_location": null,
                "review_date": null,
                "rating": "3 star rating",
                "review_text": null
            },
            {
                "user_name": null,
                "user_location": null,
                "review_date": null,
                "rating": "1 star rating",
                "review_text": null
            },
            {
                "user_name": null,
                "user_location": null,
                "review_date": null,
                "rating": "1 star rating",
                "review_text": null
            },
            {
                "user_name": null,
                "user_location": null,
                "review_date": null,
                "rating": "1 star rating",
                "review_text": null
            },
            {
                "user_name": null,
                "user_location": null,
                "review_date": null,
                "rating": "5 star rating",
                "review_text": null
            },
            {
                "user_name": null,
                "user_location": null,
                "review_date": null,
                "rating": "1 star rating",
                "review_text": null
            },
            {
                "user_name": null,
                "user_location": null,
                "review_date": null,
                "rating": "1 star rating",
                "review_text": null
            },
            {
                "user_name": null,
                "user_location": null,
                "review_date": null,
                "rating": "1 star rating",
                "review_text": null
            }
        ],
        "address": "5250 E Cherry Creek S Dr Denver, CO 80246",
        "work_hours": [
            "Mon: Closed",
            "Tue: 10:00 AM - 5:00 PM",
            "Wed: 10:00 AM - 5:00 PM",
            "Thu: 10:00 AM - 5:00 PM",
            "Fri: 10:00 AM - 5:00 PM",
            "Sat: 10:00 AM - 5:00 PM",
            "Sun: Closed"
        ]
    },
    {
        "owner_name": null,
        "business_name": "Park Realty And Property Management Denver",
        "business_website": "l.linklyhq.com/l/1vagy",
        "yelp_website": "https://www.yelp.com/biz/park-realty-and-property-management-denver?osq=Real+estate",
        "phone_number": "(303) 282-7271",
        "review_rating": null,
        "number_of_reviews": 7,
        "business_categories": [],
        "reviews": [
            {
                "user_name": null,
                "user_location": null,
                "review_date": null,
                "rating": "1 star rating",
                "review_text": null
            },
            {
                "user_name": null,
                "user_location": null,
                "review_date": null,
                "rating": "5 star rating",
                "review_text": null
            },
            {
                "user_name": null,
                "user_location": null,
                "review_date": null,
                "rating": "3 star rating",
                "review_text": null
            },
            {
                "user_name": null,
                "user_location": null,
                "review_date": null,
                "rating": "5 star rating",
                "review_text": null
            },
            {
                "user_name": null,
                "user_location": null,
                "review_date": null,
                "rating": "5 star rating",
                "review_text": null
            },
            {
                "user_name": null,
                "user_location": null,
                "review_date": null,
                "rating": "5 star rating",
                "review_text": null
            },
            {
                "user_name": null,
                "user_location": null,
                "review_date": null,
                "rating": "5 star rating",
                "review_text": null
            }
        ],
        "address": "Denver, CO 80205",
        "work_hours": [
            "Mon: 9:00 AM - 7:00 PM",
            "Tue: 9:00 AM - 7:00 PM",
            "Wed: 9:00 AM - 7:00 PM",
            "Thu: 9:00 AM - 7:00 PM",
            "Fri: 9:00 AM - 7:00 PM",
            "Sat: 9:00 AM - 7:00 PM",
            "Sun: 9:00 AM - 7:00 PM"
        ]
    },
    {
        "owner_name": "Jaime L.",
        "business_name": "Mustard Seeds Interiors Aurora",
        "business_website": "mustardseedsinteriors.com",
        "yelp_website": "https://www.yelp.com/biz/mustard-seeds-interiors-aurora?osq=Real+estate",
        "phone_number": "(303) 962-7459",
        "review_rating": null,
        "number_of_reviews": 4,
        "business_categories": [],
        "reviews": [
            {
                "user_name": null,
                "user_location": null,
                "review_date": null,
                "rating": "5 star rating",
                "review_text": null
            },
            {
                "user_name": null,
                "user_location": null,
                "review_date": null,
                "rating": "5 star rating",
                "review_text": null
            },
            {
                "user_name": null,
                "user_location": null,
                "review_date": null,
                "rating": "5 star rating",
                "review_text": null
            },
            {
                "user_name": null,
                "user_location": null,
                "review_date": null,
                "rating": "5 star rating",
                "review_text": null
            }
        ],
        "address": "",
        "work_hours": [
            "Mon: 8:00 AM - 7:00 PM",
            "Tue: 8:00 AM - 7:00 PM",
            "Wed: 9:00 AM - 7:00 PM",
            "Thu: 8:00 AM - 7:00 PM",
            "Fri: 8:00 AM - 7:00 PM",
            "Sat: Closed",
            "Sun: Closed"
        ]
    },
    {
        "owner_name": "Jeff P.",
        "business_name": "Jeff Plous Denver",
        "business_website": "hatchdenver.com",
        "yelp_website": "https://www.yelp.com/biz/jeff-plous-denver?osq=Real+estate",
        "phone_number": "(303) 317-5758",
        "review_rating": null,
        "number_of_reviews": 10,
        "business_categories": [],
        "reviews": [
            {
                "user_name": null,
                "user_location": null,
                "review_date": null,
                "rating": "5 star rating",
                "review_text": null
            },
            {
                "user_name": null,
                "user_location": null,
                "review_date": null,
                "rating": "5 star rating",
                "review_text": null
            },
            {
                "user_name": null,
                "user_location": null,
                "review_date": null,
                "rating": "5 star rating",
                "review_text": null
            },
            {
                "user_name": null,
                "user_location": null,
                "review_date": null,
                "rating": "5 star rating",
                "review_text": null
            },
            {
                "user_name": null,
                "user_location": null,
                "review_date": null,
                "rating": "5 star rating",
                "review_text": null
            },
            {
                "user_name": null,
                "user_location": null,
                "review_date": null,
                "rating": "5 star rating",
                "review_text": null
            },
            {
                "user_name": null,
                "user_location": null,
                "review_date": null,
                "rating": "5 star rating",
                "review_text": null
            },
            {
                "user_name": null,
                "user_location": null,
                "review_date": null,
                "rating": "5 star rating",
                "review_text": null
            },
            {
                "user_name": null,
                "user_location": null,
                "review_date": null,
                "rating": "5 star rating",
                "review_text": null
            },
            {
                "user_name": null,
                "user_location": null,
                "review_date": null,
                "rating": "5 star rating",
                "review_text": null
            }
        ],
        "address": "679 Grant St Denver, CO 80203",
        "work_hours": [
            "Mon: Open 24 hours",
            "Tue: Open 24 hours",
            "Wed: Open 24 hours",
            "Thu: Open 24 hours",
            "Fri: Open 24 hours",
            "Sat: Open 24 hours",
            "Sun: 12:00 AM - 12:00 AM (Next day)"
        ]
    },
    {
        "owner_name": "Ben P.",
        "business_name": "Integrity Realty And Management Greenwood Village",
        "business_website": "integrityrm.net",
        "yelp_website": "https://www.yelp.com/biz/integrity-realty-and-management-greenwood-village?osq=Real+estate",
        "phone_number": "(303) 847-0130",
        "review_rating": null,
        "number_of_reviews": 12,
        "business_categories": [],
        "reviews": [
            {
                "user_name": null,
                "user_location": null,
                "review_date": null,
                "rating": null,
                "review_text": null
            },
            {
                "user_name": null,
                "user_location": null,
                "review_date": null,
                "rating": null,
                "review_text": null
            },
            {
                "user_name": null,
                "user_location": null,
                "review_date": null,
                "rating": "5 star rating",
                "review_text": null
            },
            {
                "user_name": null,
                "user_location": null,
                "review_date": null,
                "rating": "5 star rating",
                "review_text": null
            },
            {
                "user_name": null,
                "user_location": null,
                "review_date": null,
                "rating": "5 star rating",
                "review_text": null
            },
            {
                "user_name": null,
                "user_location": null,
                "review_date": null,
                "rating": "5 star rating",
                "review_text": null
            },
            {
                "user_name": null,
                "user_location": null,
                "review_date": null,
                "rating": "5 star rating",
                "review_text": null
            },
            {
                "user_name": null,
                "user_location": null,
                "review_date": null,
                "rating": "1 star rating",
                "review_text": null
            },
            {
                "user_name": null,
                "user_location": null,
                "review_date": null,
                "rating": "5 star rating",
                "review_text": null
            },
            {
                "user_name": null,
                "user_location": null,
                "review_date": null,
                "rating": "5 star rating",
                "review_text": null
            },
            {
                "user_name": null,
                "user_location": null,
                "review_date": null,
                "rating": "5 star rating",
                "review_text": null
            },
            {
                "user_name": null,
                "user_location": null,
                "review_date": null,
                "rating": "5 star rating",
                "review_text": null
            }
        ],
        "address": "9250 E Costilla Ave Greenwood Village, CO 80112",
        "work_hours": [
            "Mon: 9:00 AM - 5:00 PM",
            "Tue: 9:00 AM - 5:00 PM",
            "Wed: 9:00 AM - 5:00 PM",
            "Thu: 9:00 AM - 5:00 PM",
            "Fri: 9:00 AM - 5:00 PM",
            "Sat: Closed",
            "Sun: Closed"
        ]
    },
    {
        "owner_name": "Sana K.",
        "business_name": "Sana Wood Kentwood Real Estate Denver",
        "business_website": "sanawood.com",
        "yelp_website": "https://www.yelp.com/biz/sana-wood-kentwood-real-estate-denver?osq=Real+estate",
        "phone_number": "(303) 881-3514",
        "review_rating": null,
        "number_of_reviews": 8,
        "business_categories": [],
        "reviews": [
            {
                "user_name": null,
                "user_location": null,
                "review_date": null,
                "rating": "5 star rating",
                "review_text": null
            },
            {
                "user_name": null,
                "user_location": null,
                "review_date": null,
                "rating": "5 star rating",
                "review_text": null
            },
            {
                "user_name": null,
                "user_location": null,
                "review_date": null,
                "rating": "5 star rating",
                "review_text": null
            },
            {
                "user_name": null,
                "user_location": null,
                "review_date": null,
                "rating": "5 star rating",
                "review_text": null
            },
            {
                "user_name": null,
                "user_location": null,
                "review_date": null,
                "rating": "5 star rating",
                "review_text": null
            },
            {
                "user_name": null,
                "user_location": null,
                "review_date": null,
                "rating": "5 star rating",
                "review_text": null
            },
            {
                "user_name": null,
                "user_location": null,
                "review_date": null,
                "rating": "5 star rating",
                "review_text": null
            },
            {
                "user_name": null,
                "user_location": null,
                "review_date": null,
                "rating": "5 star rating",
                "review_text": null
            }
        ],
        "address": "215 St Paul St Denver, CO 80206",
        "work_hours": [
            "Mon: 8:00 AM - 9:30 PM",
            "Tue: 8:00 AM - 9:30 PM",
            "Wed: 8:00 AM - 9:30 PM",
            "Thu: 8:00 AM - 9:30 PM",
            "Fri: 8:00 AM - 9:30 PM",
            "Sat: 8:00 AM - 9:30 PM",
            "Sun: 8:00 AM - 9:30 PM"
        ]
    },
    {
        "owner_name": "David S.",
        "business_name": "The Schlichter Team Denver",
        "business_website": "schlichterteam.com",
        "yelp_website": "https://www.yelp.com/biz/the-schlichter-team-denver?osq=Real+estate",
        "phone_number": "(720) 502-0505",
        "review_rating": null,
        "number_of_reviews": 11,
        "business_categories": [],
        "reviews": [
            {
                "user_name": null,
                "user_location": null,
                "review_date": null,
                "rating": null,
                "review_text": null
            },
            {
                "user_name": null,
                "user_location": null,
                "review_date": null,
                "rating": "5 star rating",
                "review_text": null
            },
            {
                "user_name": null,
                "user_location": null,
                "review_date": null,
                "rating": "5 star rating",
                "review_text": null
            },
            {
                "user_name": null,
                "user_location": null,
                "review_date": null,
                "rating": "5 star rating",
                "review_text": null
            },
            {
                "user_name": null,
                "user_location": null,
                "review_date": null,
                "rating": "5 star rating",
                "review_text": null
            },
            {
                "user_name": null,
                "user_location": null,
                "review_date": null,
                "rating": "5 star rating",
                "review_text": null
            },
            {
                "user_name": null,
                "user_location": null,
                "review_date": null,
                "rating": "5 star rating",
                "review_text": null
            },
            {
                "user_name": null,
                "user_location": null,
                "review_date": null,
                "rating": "5 star rating",
                "review_text": null
            },
            {
                "user_name": null,
                "user_location": null,
                "review_date": null,
                "rating": "5 star rating",
                "review_text": null
            },
            {
                "user_name": null,
                "user_location": null,
                "review_date": null,
                "rating": "5 star rating",
                "review_text": null
            },
            {
                "user_name": null,
                "user_location": null,
                "review_date": null,
                "rating": "5 star rating",
                "review_text": null
            }
        ],
        "address": "200 Columbine St Ste 500 Denver, CO 80206",
        "work_hours": [
            "Mon: 9:00 AM - 7:00 PM",
            "Tue: 9:00 AM - 7:00 PM",
            "Wed: 9:00 AM - 7:00 PM",
            "Thu: 9:00 AM - 7:00 PM",
            "Fri: 9:00 AM - 7:00 PM",
            "Sat: 9:00 AM - 7:00 PM",
            "Sun: 9:00 AM - 7:00 PM"
        ]
    },
    {
        "owner_name": "Marina G.",
        "business_name": "Evolve Real Estate And Property Management Denver 3",
        "business_website": "evolvedenver.com",
        "yelp_website": "https://www.yelp.com/biz/evolve-real-estate-and-property-management-denver-3?osq=Real+estate",
        "phone_number": "(720) 800-6390",
        "review_rating": null,
        "number_of_reviews": 10,
        "business_categories": [],
        "reviews": [
            {
                "user_name": null,
                "user_location": null,
                "review_date": null,
                "rating": "5 star rating",
                "review_text": null
            },
            {
                "user_name": null,
                "user_location": null,
                "review_date": null,
                "rating": "3 star rating",
                "review_text": null
            },
            {
                "user_name": null,
                "user_location": null,
                "review_date": null,
                "rating": "5 star rating",
                "review_text": null
            },
            {
                "user_name": null,
                "user_location": null,
                "review_date": null,
                "rating": "1 star rating",
                "review_text": null
            },
            {
                "user_name": null,
                "user_location": null,
                "review_date": null,
                "rating": "5 star rating",
                "review_text": null
            },
            {
                "user_name": null,
                "user_location": null,
                "review_date": null,
                "rating": "5 star rating",
                "review_text": null
            },
            {
                "user_name": null,
                "user_location": null,
                "review_date": null,
                "rating": "5 star rating",
                "review_text": null
            },
            {
                "user_name": null,
                "user_location": null,
                "review_date": null,
                "rating": "5 star rating",
                "review_text": null
            },
            {
                "user_name": null,
                "user_location": null,
                "review_date": null,
                "rating": "1 star rating",
                "review_text": null
            },
            {
                "user_name": null,
                "user_location": null,
                "review_date": null,
                "rating": "5 star rating",
                "review_text": null
            }
        ],
        "address": "100 Fillmore St Ste 500 Denver, CO 80206",
        "work_hours": [
            "Mon: 9:00 AM - 5:00 PM",
            "Tue: 9:00 AM - 5:00 PM",
            "Wed: 9:00 AM - 5:00 PM",
            "Thu: 9:00 AM - 5:00 PM",
            "Fri: 9:00 AM - 5:00 PM",
            "Sat: Closed",
            "Sun: Closed"
        ]
    }
]